ppocrtool/__init__.py
ppocrtool/ppocrtool.py
ppocr_tool-1.0.1.dist-info/METADATA
ppocr_tool-1.0.1.dist-info/WHEEL
ppocr_tool-1.0.1.dist-info/entry_points.txt
ppocr_tool-1.0.1.dist-info/top_level.txt
ppocr_tool-1.0.1.dist-info/RECORD
