Metadata-Version: 2.1
Name: ppocr-tool
Version: 1.0.1
Requires-Dist: paddlepaddle
Requires-Dist: paddleocr
